Metadata-Version: 2.1
Name: thoipapy
Version: 1.2.0
Summary: Machine-learning prediction of residues driving homotypic transmembrane interactions.
Home-page: https://github.com/bojigu/thoipapy
Author: Bo Zeng
Author-email: zeng@checkmytumhomepage.de
License: MIT
Download-URL: https://github.com/bojigu/thoipapy/archive/1.1.3.tar.gz
Project-URL: BoZeng, http://frishman.wzw.tum.de/index.php?id=50
Project-URL: FrishmanLab, http://frishman.wzw.tum.de/index.php?id=2
Project-URL: LangoschLab, http://cbp.wzw.tum.de/index.php?id=10
Project-URL: TU_Munich, https://www.tum.de
Keywords: bioinformatics protein transmembrane residue conservation coevolution covariance evolutionary couplings polarity hydrophobicity randomforest machinelearning interface LIPS evolution
Platform: UNKNOWN
Classifier: Programming Language :: Python :: 3.8
Classifier: License :: OSI Approved :: MIT License
Classifier: Intended Audience :: Science/Research
Classifier: Topic :: Scientific/Engineering :: Chemistry
Classifier: Topic :: Scientific/Engineering :: Physics
Classifier: Topic :: Scientific/Engineering :: Bio-Informatics
Requires-Python: >=3
Requires-Dist: pandas
Requires-Dist: numpy
Requires-Dist: scipy
Requires-Dist: seaborn
Requires-Dist: biopython
Requires-Dist: matplotlib
Requires-Dist: django
Requires-Dist: pytoxr
Requires-Dist: statsmodels
Requires-Dist: scikit-learn
Requires-Dist: weighslide
Requires-Dist: pytest
Requires-Dist: psutil
